include/defines.vh
/*
-------------------------------------------------------------------------
Disciplina: Arquitetura e Organização de Computadores - 2025.2
Atividade: Projeto 02 - Implementação de MIPS em Verilog
Grupo: [INSERIR NOMES AQUI]
Arquivo: defines.vh
Descrição: Definições de macros (constantes) para Opcodes, Functs e ALU.
-------------------------------------------------------------------------
*/
`ifndef DEFINES_VH
`define DEFINES_VH

// --- PARÂMETROS DE MEMÓRIA ---
`define IMEM_SIZE 1024
`define DMEM_SIZE 1024

// --- ALUOp CODES (Control -> ALU Ctrl) ---
`define ALUOP_RTYPE         2'b10
`define ALUOP_BEQ_BNE       2'b01
`define ALUOP_LW_SW_ADDI    2'b00
`define ALUOP_ANDI_ORI_XORI 2'b11

// --- ULA INTERNAL CODES (ALU Ctrl -> ULA) ---
`define ALU_ADD   4'b0001
`define ALU_SUB   4'b0010
`define ALU_AND   4'b0011
`define ALU_OR    4'b0100
`define ALU_XOR   4'b0101
`define ALU_NOR   4'b0110
`define ALU_SLT   4'b0111
`define ALU_SLTU  4'b1000
`define ALU_SLL   4'b1001
`define ALU_SRL   4'b1010
`define ALU_SRA   4'b1011
`define ALU_SLLV  4'b1100
`define ALU_SRLV  4'b1101
`define ALU_SRAV  4'b1110
`define ALU_JR    4'b1111

// --- FUNCT FOR R-TYPE (6 bits) ---
`define FUNCT_ADD   6'b100000
`define FUNCT_SUB   6'b100010
`define FUNCT_AND   6'b100100
`define FUNCT_OR    6'b100101
`define FUNCT_XOR   6'b100110
`define FUNCT_NOR   6'b100111
`define FUNCT_SLT   6'b101010
`define FUNCT_SLTU  6'b101011
`define FUNCT_SLL   6'b000000
`define FUNCT_SRL   6'b000010
`define FUNCT_SRA   6'b000011
`define FUNCT_SLLV  6'b000100
`define FUNCT_SRLV  6'b000110
`define FUNCT_SRAV  6'b000111
`define FUNCT_JR    6'b001000

// --- MIPS OPCODES (6 bits) ---
`define MIPS_RTYPE  6'b000000
`define MIPS_ADDI   6'b001000
`define MIPS_ANDI   6'b001100
`define MIPS_ORI    6'b001101
`define MIPS_XORI   6'b001110
`define MIPS_BEQ    6'b000100
`define MIPS_BNE    6'b000101
`define MIPS_SLTI   6'b001010
`define MIPS_SLTIU  6'b001011
`define MIPS_LUI    6'b001111
`define MIPS_LW     6'b100011
`define MIPS_SW     6'b101011
`define MIPS_J      6'b000010
`define MIPS_JAL    6'b000011

`endif

src/control.v
/*
-------------------------------------------------------------------------
Disciplina: Arquitetura e Organização de Computadores - 2025.2
Atividade: Projeto 02 - Implementação de MIPS em Verilog
Grupo: [INSERIR NOMES AQUI]
Arquivo: control.v
Descrição: Decodifica o Opcode e gera sinais de controle para o Datapath.
-------------------------------------------------------------------------
*/
`include "defines.vh"

module control(
  input [5:0] opcode,
  input [5:0] funct,
  output reg RegDst, Jump, Branch, MemRead, MemtoReg,
  output reg [1:0] ALUOp,
  output reg MemWrite, ALUSrc, RegWrite, Jr, ExtOp, JalEn, LuiEn
);
  always @(*) begin
    // Reset padrão
    RegDst=0; Jump=0; Branch=0; MemRead=0; MemtoReg=0;
    ALUOp=`ALUOP_LW_SW_ADDI; MemWrite=0; ALUSrc=0; RegWrite=0;
    Jr=0; ExtOp=1; JalEn=0; LuiEn=0;

    case (opcode)
      `MIPS_RTYPE: begin
        RegDst = 1; RegWrite = 1; ALUOp = `ALUOP_RTYPE;
        Jr = (funct == `FUNCT_JR) ? 1 : 0;
      end
      `MIPS_ADDI: begin ALUSrc = 1; RegWrite = 1; end
      `MIPS_ANDI: begin ALUSrc = 1; RegWrite = 1; ExtOp = 0; ALUOp = `ALUOP_ANDI_ORI_XORI; end
      `MIPS_ORI:  begin ALUSrc = 1; RegWrite = 1; ExtOp = 0; ALUOp = `ALUOP_ANDI_ORI_XORI; end
      `MIPS_XORI: begin ALUSrc = 1; RegWrite = 1; ExtOp = 0; ALUOp = `ALUOP_ANDI_ORI_XORI; end
      `MIPS_BEQ:  begin Branch = 1; ALUOp = `ALUOP_BEQ_BNE; end
      `MIPS_BNE:  begin Branch = 1; ALUOp = `ALUOP_BEQ_BNE; end
      `MIPS_SLTI: begin ALUSrc = 1; RegDst = 0; RegWrite = 1; ALUOp = 2'b10; end
      `MIPS_SLTIU:begin ALUSrc = 1; RegDst = 0; RegWrite = 1; ALUOp = 2'b11; end
      `MIPS_LUI:  begin ALUSrc = 1; RegWrite = 1; LuiEn = 1; end
      `MIPS_LW:   begin ALUSrc = 1; MemtoReg = 1; RegWrite = 1; MemRead = 1; end
      `MIPS_SW:   begin ALUSrc = 1; MemWrite = 1; end
      `MIPS_J:    begin Jump = 1; end
      `MIPS_JAL:  begin Jump = 1; RegWrite = 1; JalEn = 1; end
      default: begin end
    endcase
  end
endmodule

src/d_mem.v
/*
-------------------------------------------------------------------------
Disciplina: Arquitetura e Organização de Computadores - 2025.2
Atividade: Projeto 02 - Implementação de MIPS em Verilog
Grupo: [INSERIR NOMES AQUI]
Arquivo: d_mem.v
Descrição: Memória RAM para armazenamento de dados (Load/Store).
-------------------------------------------------------------------------
*/
`include "defines.vh"

module d_mem(
  input clock,
  input MemRead,          // Habilita leitura
  input MemWrite,         // Habilita escrita
  input [31:0] address,   // Endereço
  input [31:0] WriteData, // Dado a ser escrito
  output [31:0] ReadData  // Dado lido
);
  reg [31:0] mem [0:`DMEM_SIZE-1];
  integer k;

  initial begin
     for (k=0; k<`DMEM_SIZE; k=k+1) mem[k] = 32'b0;
  end

  assign ReadData = MemRead ? mem[address[11:2]] : 32'bz;
  
  always @(posedge clock) begin
    if (MemWrite) 
      mem[address[11:2]] <= WriteData;
  end
endmodule

src/ula.v
/*
-------------------------------------------------------------------------
Disciplina: Arquitetura e Organização de Computadores - 2025.2
Atividade: Projeto 02 - Implementação de MIPS em Verilog
Grupo: [INSERIR NOMES AQUI]
Arquivo: ula.v
Descrição: Executa operações aritméticas e lógicas baseadas no sinal OP.
-------------------------------------------------------------------------
*/
`include "defines.vh"

module ula( 
  input [31:0] In1, In2,   // Operandos
  input [4:0]  shamt,      // Shift amount
  input [3:0]  OP,         // Código da operação
  output reg [31:0] result,// Resultado
  output wire Zero_Flag    // Flag Zero
);
  always @(*) begin
    case (OP)
      `ALU_ADD:   result = In1 + In2;
      `ALU_SUB:   result = In1 - In2;
      `ALU_AND:   result = In1 & In2;
      `ALU_OR:    result = In1 | In2;
      `ALU_XOR:   result = In1 ^ In2;
      `ALU_NOR:   result = ~(In1 | In2);
      `ALU_SLT:   result = ($signed(In1) < $signed(In2)) ? 1 : 0;
      `ALU_SLTU:  result = (In1 < In2) ? 1 : 0;
      `ALU_SLL:   result = In2 << shamt;
      `ALU_SRL:   result = In2 >> shamt;
      `ALU_SRA:   result = $signed(In2) >>> shamt;
      `ALU_SLLV:  result = In2 << In1[4:0];
      `ALU_SRLV:  result = In2 >> In1[4:0];
      `ALU_SRAV:  result = $signed(In2) >>> In1[4:0];
      `ALU_JR:    result = In1; 
      default:    result = 0;
    endcase
  end
  
  assign Zero_Flag = (result == 0);
endmodule

src/ula_ctrl.v
/*
-------------------------------------------------------------------------
Disciplina: Arquitetura e Organização de Computadores - 2025.2
Atividade: Projeto 02 - Implementação de MIPS em Verilog
Grupo: [INSERIR NOMES AQUI]
Arquivo: ula_ctrl.v
Descrição: Decodifica ALUOp e Funct para gerar o sinal de controle da ULA.
-------------------------------------------------------------------------
*/
`include "defines.vh"

module ula_ctrl(
  input [1:0] ALUOp,     // Vindo da Unidade de Controle
  input [5:0] funct,     // Campo funct da instrução
  output reg [3:0] OP_ula // Código para a ULA
);
  always @(*) begin
    case (ALUOp)
      `ALUOP_LW_SW_ADDI: OP_ula = `ALU_ADD; 
      `ALUOP_BEQ_BNE:    OP_ula = `ALU_SUB; 
      `ALUOP_ANDI_ORI_XORI: OP_ula = `ALU_OR; // Assumindo OR para imediatos lógicos genéricos
      
      `ALUOP_RTYPE: begin
        case (funct)
          `FUNCT_ADD:  OP_ula = `ALU_ADD;
          `FUNCT_SUB:  OP_ula = `ALU_SUB;
          `FUNCT_AND:  OP_ula = `ALU_AND;
          `FUNCT_OR:   OP_ula = `ALU_OR;
          `FUNCT_XOR:  OP_ula = `ALU_XOR;
          `FUNCT_NOR:  OP_ula = `ALU_NOR;
          `FUNCT_SLT:  OP_ula = `ALU_SLT;
          `FUNCT_SLTU: OP_ula = `ALU_SLTU;
          `FUNCT_SLL:  OP_ula = `ALU_SLL;
          `FUNCT_SRL:  OP_ula = `ALU_SRL;
          `FUNCT_SRA:  OP_ula = `ALU_SRA;
          `FUNCT_SLLV: OP_ula = `ALU_SLLV;
          `FUNCT_SRLV: OP_ula = `ALU_SRLV;
          `FUNCT_SRAV: OP_ula = `ALU_SRAV;
          `FUNCT_JR:   OP_ula = `ALU_JR;
          default:     OP_ula = `ALU_ADD;
        endcase
      end
      default: OP_ula = `ALU_ADD;
    endcase
  end
endmodule

src/sign_extend.v
/*
-------------------------------------------------------------------------
Disciplina: Arquitetura e Organização de Computadores - 2025.2
Atividade: Projeto 02 - Implementação de MIPS em Verilog
Grupo: [INSERIR NOMES AQUI]
Arquivo: sign_extend.v
Descrição: Estende imediatos de 16 bits para 32 bits (com sinal ou zero).
-------------------------------------------------------------------------
*/
module sign_extend(
  input [15:0] imm,
  input ExtOp,       // 1 = Sinal, 0 = Zero
  output reg [31:0] ext_out
);
  always @(*) begin
    if (ExtOp) 
      ext_out = {{16{imm[15]}}, imm}; // Extensão de sinal
    else       
      ext_out = {16'b0, imm};         // Extensão de zero
  end
endmodule

src/regfile.v
/*
-------------------------------------------------------------------------
Disciplina: Arquitetura e Organização de Computadores - 2025.2
Atividade: Projeto 02 - Implementação de MIPS em Verilog
Grupo: [INSERIR NOMES AQUI]
Arquivo: regfile.v
Descrição: Banco com 32 registradores de 32 bits. Reg $0 é sempre zero.
-------------------------------------------------------------------------
*/
module regfile(
  input clock,
  input reset,
  input RegWrite,            // Habilita escrita
  input [4:0] ReadAddr1,     // Endereço rs
  input [4:0] ReadAddr2,     // Endereço rt
  input [4:0] WriteAddr,     // Endereço rd (ou rt em tipo-I)
  input [31:0] WriteData,    // Dado a ser escrito
  output [31:0] ReadData1,   // Saída rs
  output [31:0] ReadData2    // Saída rt
);
  reg [31:0] registers [0:31]; 
  integer i;

  // Leitura Assíncrona
  assign ReadData1 = (ReadAddr1 == 0) ? 32'b0 : registers[ReadAddr1];
  assign ReadData2 = (ReadAddr2 == 0) ? 32'b0 : registers[ReadAddr2];

  // Escrita Síncrona
  always @(posedge clock or posedge reset) begin
    if (reset) begin
      for (i=0; i<32; i=i+1) registers[i] <= 0;
    end 
    else if (RegWrite && WriteAddr != 0) begin
      registers[WriteAddr] <= WriteData;
    end
  end
endmodule

src/i_mem.v
/*
-------------------------------------------------------------------------
Disciplina: Arquitetura e Organização de Computadores - 2025.2
Atividade: Projeto 02 - Implementação de MIPS em Verilog
Grupo: [INSERIR NOMES AQUI]
Arquivo: i_mem.v
Descrição: Memória de Instrução (ROM). Lê o programa de 'instruction.list'.
-------------------------------------------------------------------------
*/
`include "defines.vh"

module i_mem(
  input  wire [31:0] address,   // Endereço vindo do PC
  output wire [31:0] i_out      // Instrução lida
);
  reg [31:0] mem [0:`IMEM_SIZE-1];
  integer i;

  initial begin
    // Inicializa com zeros
    for (i = 0; i < `IMEM_SIZE; i = i + 1) mem[i] = 32'b0;

    // Carrega o arquivo externo (Requisito do PDF)
    $readmemb("instruction.list", mem);
  end
  
  // Leitura assíncrona (word align: address / 4)
  assign i_out = mem[address[11:2]]; 
endmodule

src/pc.v
/*
-------------------------------------------------------------------------
Disciplina: Arquitetura e Organização de Computadores - 2025.2
Atividade: Projeto 02 - Implementação de MIPS em Verilog
Grupo: [INSERIR NOMES AQUI]
Arquivo: pc.v
Descrição: Registrador de 32 bits que armazena o endereço da instrução atual.
-------------------------------------------------------------------------
*/
module pc(
  input clock,          // Clock do sistema
  input reset,          // Reset global
  input [31:0] nextPC,  // Próximo endereço calculado
  output reg [31:0] PC  // Endereço atual
);
  always @(posedge clock or posedge reset) begin
    if (reset) 
      PC <= 32'h00000000; 
    else       
      PC <= nextPC;       
  end
endmodule

src/mips.v
/*
-------------------------------------------------------------------------
Disciplina: Arquitetura e Organização de Computadores - 2025.2
Atividade: Projeto 02 - Implementação de MIPS em Verilog
Grupo: [INSERIR NOMES AQUI]
Arquivo: mips.v
Descrição: Módulo Top-Level. Integra Datapath e Controle.
-------------------------------------------------------------------------
*/
`include "defines.vh"

module mips(
  input clock,
  input reset,
  output [31:0] PCOut,
  output [31:0] ALUResultOut,
  output [31:0] MemOut
);
  // Fios de interconexão
  wire [31:0] PC, nextPC, instruction;
  wire [31:0] read_data1, read_data2, write_data;
  wire [31:0] sign_ext_out, alu_in2, dmem_out;
  wire RegDst, Jump, Branch, MemRead, MemtoReg, MemWrite, ALUSrc, RegWrite, Jr, ExtOp, JalEn, LuiEn;
  wire [1:0] ALUOp;
  wire [3:0] alu_control;
  wire zero_flag;

  // 1. Contador de Programa (PC)
  pc pc_inst(.clock(clock), .reset(reset), .nextPC(nextPC), .PC(PC));
  assign PCOut = PC;
  
  // 2. Memória de Instrução
  i_mem imem(.address(PC), .i_out(instruction));
  
  // Mux do registrador de escrita
  wire [4:0] write_reg = JalEn ? 5'b11111 : (RegDst ? instruction[15:11] : instruction[20:16]);
  
  // 3. Banco de Registradores
  regfile regs(
    .clock(clock), .reset(reset), .RegWrite(RegWrite),
    .ReadAddr1(instruction[25:21]), .ReadAddr2(instruction[20:16]),
    .WriteAddr(write_reg), .WriteData(write_data),
    .ReadData1(read_data1), .ReadData2(read_data2)
  );
  
  // 4. Extensão de Sinal
  sign_extend ext(.imm(instruction[15:0]), .ExtOp(ExtOp), .ext_out(sign_ext_out));
  
  // Mux da entrada B da ULA
  assign alu_in2 = ALUSrc ? sign_ext_out : read_data2;
  
  // 5. Controle e ULA
  ula_ctrl uctrl(.ALUOp(ALUOp), .funct(instruction[5:0]), .OP_ula(alu_control));
  
  ula alu(
    .In1(read_data1), .In2(alu_in2), .shamt(instruction[10:6]),
    .OP(alu_control), .result(ALUResultOut), .Zero_Flag(zero_flag)
  );
  
  // 6. Memória de Dados
  d_mem dmem(
    .clock(clock), .MemRead(MemRead), .MemWrite(MemWrite),
    .address(ALUResultOut), .WriteData(read_data2), .ReadData(dmem_out)
  );
  assign MemOut = dmem_out;
  
  // 7. Lógica de Próximo PC
  wire [31:0] pc_plus4 = PC + 4;
  wire [31:0] branch_target = pc_plus4 + {sign_ext_out[29:0], 2'b00};
  wire is_jr = (instruction[31:26] == `MIPS_RTYPE) && (instruction[5:0] == `FUNCT_JR);
  wire branch_taken = Branch & (
    (instruction[31:26] == `MIPS_BEQ & zero_flag) | 
    (instruction[31:26] == `MIPS_BNE & ~zero_flag)
  );
  
  assign nextPC = is_jr ? read_data1 :
                  Jump  ? {pc_plus4[31:28], instruction[25:0], 2'b00} :
                  branch_taken ? branch_target :
                  pc_plus4;
  
  assign write_data = JalEn ? pc_plus4 : 
                      LuiEn ? {instruction[15:0], 16'b0} : 
                      MemtoReg ? dmem_out : ALUResultOut;
  
  // 8. Unidade de Controle Principal
  control ctrl(
    .opcode(instruction[31:26]), .funct(instruction[5:0]),
    .RegDst(RegDst), .Jump(Jump), .Branch(Branch),
    .MemRead(MemRead), .MemtoReg(MemtoReg), .ALUOp(ALUOp),
    .MemWrite(MemWrite), .ALUSrc(ALUSrc), .RegWrite(RegWrite),
    .Jr(Jr), .ExtOp(ExtOp), .JalEn(JalEn), .LuiEn(LuiEn)
  );

endmodule

test/testbench.v
/*
-------------------------------------------------------------------------
Disciplina: Arquitetura e Organização de Computadores - 2025.2
Atividade: Projeto 02 - Implementação de MIPS em Verilog
Grupo: [INSERIR NOMES AQUI]
Arquivo: testbench.v
Descrição: Gera clock/reset e monitora a execução do processador.
           Configurado com tempo estendido para programas maiores.
-------------------------------------------------------------------------
*/
`include "defines.vh"

module testbench;
  reg clock;
  reg reset;
  wire [31:0] PCOut;
  wire [31:0] ALUResultOut;
  wire [31:0] MemOut;

  // Instância do DUT (Device Under Test) - O Processador MIPS
  mips dut(
    .clock(clock),
    .reset(reset),
    .PCOut(PCOut),
    .ALUResultOut(ALUResultOut),
    .MemOut(MemOut)
  );

  // Geração de Clock (Período = 10ns)
  initial begin
    clock = 0;
    forever #5 clock = ~clock;
  end

  // Sequência de Controle da Simulação
  initial begin
    // Configura arquivo para visualização de ondas no GTKWave
    $dumpfile("mips_waveform.vcd");
    $dumpvars(0, testbench);

    // Reset inicial
    $display(">>> Iniciando Simulação...");
    reset = 1;
    #10;
    reset = 0;
    
    // -----------------------------------------------------------
    // TEMPO DE SIMULAÇÃO AUMENTADO
    // Como a instruction.list é grande, aumentamos para 5000ns.
    // Se o programa não terminar, aumente este valor (ex: #10000).
    // -----------------------------------------------------------
    #800; 
    
    $display("---------------------------------------------------------");
    $display("Simulação finalizada por limite de tempo.");
    $finish;
  end

  // Monitoramento (Imprime no terminal a cada ciclo de clock)
  always @(posedge clock) begin
    if (!reset) begin
      // Exibe estado básico: Tempo, PC, Instrução (Hex), Resultado ULA
      $write("Time: %4d | PC: %h | Instr: %h | ULA: %h ", 
               $time, PCOut, dut.instruction, ALUResultOut);

      // Feedback específico para operações de Memória
      if (dut.MemWrite) begin
          $display("| [MEM WRITE] Escreveu %h no end. %h", dut.dmem.WriteData, ALUResultOut);
      end
      else if (dut.MemRead) begin
          $display("| [MEM READ] Leu %h do end. %h", MemOut, ALUResultOut);
      end
      else begin
          $display(""); // Apenas pular linha
      end
    end
  end
endmodule

mips_waveform.vcd
$date
	Tue Dec 09 13:14:46 2025
$end
$version
	Icarus Verilog
$end
$timescale
	1s
$end
$scope module testbench $end
$var wire 32 ! PCOut [31:0] $end
$var wire 32 " MemOut [31:0] $end
$var wire 32 # ALUResultOut [31:0] $end
$var reg 1 $ clock $end
$var reg 1 % reset $end
$scope module dut $end
$var wire 32 & MemOut [31:0] $end
$var wire 32 ' PCOut [31:0] $end
$var wire 1 ( branch_taken $end
$var wire 1 $ clock $end
$var wire 1 ) is_jr $end
$var wire 1 % reset $end
$var wire 1 * zero_flag $end
$var wire 5 + write_reg [4:0] $end
$var wire 32 , write_data [31:0] $end
$var wire 32 - sign_ext_out [31:0] $end
$var wire 32 . read_data2 [31:0] $end
$var wire 32 / read_data1 [31:0] $end
$var wire 32 0 pc_plus4 [31:0] $end
$var wire 32 1 nextPC [31:0] $end
$var wire 32 2 instruction [31:0] $end
$var wire 32 3 dmem_out [31:0] $end
$var wire 32 4 branch_target [31:0] $end
$var wire 32 5 alu_in2 [31:0] $end
$var wire 4 6 alu_control [3:0] $end
$var wire 1 7 RegWrite $end
$var wire 1 8 RegDst $end
$var wire 32 9 PC [31:0] $end
$var wire 1 : MemtoReg $end
$var wire 1 ; MemWrite $end
$var wire 1 < MemRead $end
$var wire 1 = LuiEn $end
$var wire 1 > Jump $end
$var wire 1 ? Jr $end
$var wire 1 @ JalEn $end
$var wire 1 A ExtOp $end
$var wire 1 B Branch $end
$var wire 1 C ALUSrc $end
$var wire 32 D ALUResultOut [31:0] $end
$var wire 2 E ALUOp [1:0] $end
$scope module alu $end
$var wire 32 F In2 [31:0] $end
$var wire 5 G shamt [4:0] $end
$var wire 1 * Zero_Flag $end
$var wire 4 H OP [3:0] $end
$var wire 32 I In1 [31:0] $end
$var reg 32 J result [31:0] $end
$upscope $end
$scope module ctrl $end
$var wire 6 K funct [5:0] $end
$var wire 6 L opcode [5:0] $end
$var reg 2 M ALUOp [1:0] $end
$var reg 1 C ALUSrc $end
$var reg 1 B Branch $end
$var reg 1 A ExtOp $end
$var reg 1 @ JalEn $end
$var reg 1 ? Jr $end
$var reg 1 > Jump $end
$var reg 1 = LuiEn $end
$var reg 1 < MemRead $end
$var reg 1 ; MemWrite $end
$var reg 1 : MemtoReg $end
$var reg 1 8 RegDst $end
$var reg 1 7 RegWrite $end
$upscope $end
$scope module dmem $end
$var wire 1 < MemRead $end
$var wire 1 ; MemWrite $end
$var wire 32 N address [31:0] $end
$var wire 1 $ clock $end
$var wire 32 O WriteData [31:0] $end
$var wire 32 P ReadData [31:0] $end
$var integer 32 Q k [31:0] $end
$upscope $end
$scope module ext $end
$var wire 1 A ExtOp $end
$var wire 16 R imm [15:0] $end
$var reg 32 S ext_out [31:0] $end
$upscope $end
$scope module imem $end
$var wire 32 T i_out [31:0] $end
$var wire 32 U address [31:0] $end
$var integer 32 V i [31:0] $end
$upscope $end
$scope module pc_inst $end
$var wire 1 $ clock $end
$var wire 32 W nextPC [31:0] $end
$var wire 1 % reset $end
$var reg 32 X PC [31:0] $end
$upscope $end
$scope module regs $end
$var wire 5 Y ReadAddr1 [4:0] $end
$var wire 5 Z ReadAddr2 [4:0] $end
$var wire 1 7 RegWrite $end
$var wire 5 [ WriteAddr [4:0] $end
$var wire 32 \ WriteData [31:0] $end
$var wire 1 $ clock $end
$var wire 1 % reset $end
$var wire 32 ] ReadData2 [31:0] $end
$var wire 32 ^ ReadData1 [31:0] $end
$var integer 32 _ i [31:0] $end
$upscope $end
$scope module uctrl $end
$var wire 2 ` ALUOp [1:0] $end
$var wire 6 a funct [5:0] $end
$var reg 4 b OP_ula [3:0] $end
$upscope $end
$upscope $end
$upscope $end
$enddefinitions $end
$comment Show the parameter values. $end
$dumpall
$end
#0
$dumpvars
b1001 b
b0 a
b10 `
b100000 _
b0 ^
b0 ]
b0 \
b0 [
b0 Z
b0 Y
b0 X
b100 W
b10000000000 V
b0 U
b0 T
b0 S
b0 R
b10000000000 Q
bz P
b0 O
b0 N
b10 M
b0 L
b0 K
b0 J
b0 I
b1001 H
b0 G
b0 F
b10 E
b0 D
0C
0B
1A
0@
0?
0>
0=
0<
0;
0:
b0 9
18
17
b1001 6
b0 5
b100 4
bz 3
b0 2
b100 1
b100 0
b0 /
b0 .
b0 -
b0 ,
b0 +
1*
0)
0(
b0 '
bz &
1%
0$
b0 #
bz "
b0 !
$end
#5
b100000 _
1$
#10
0$
0%
#15
b1000 1
b1000 W
b1000 4
b1000 0
b100 !
b100 '
b100 9
b100 U
b100 X
1$
#20
0$
#25
b1100 1
b1100 W
b1100 4
b1100 0
b1000 !
b1000 '
b1000 9
b1000 U
b1000 X
1$
#30
0$
#35
b10000 1
b10000 W
b10000 4
b10000 0
b1100 !
b1100 '
b1100 9
b1100 U
b1100 X
1$
#40
0$
#45
b10100 1
b10100 W
b10100 4
b10100 0
b10000 !
b10000 '
b10000 9
b10000 U
b10000 X
1$
#50
0$
#55
b11000 1
b11000 W
b11000 4
b11000 0
b10100 !
b10100 '
b10100 9
b10100 U
b10100 X
1$
#60
0$
#65
b11100 1
b11100 W
b11100 4
b11100 0
b11000 !
b11000 '
b11000 9
b11000 U
b11000 X
1$
#70
0$
#75
b100000 1
b100000 W
b100000 4
b100000 0
b11100 !
b11100 '
b11100 9
b11100 U
b11100 X
1$
#80
0$
#85
b100100 1
b100100 W
b100100 4
b100100 0
b100000 !
b100000 '
b100000 9
b100000 U
b100000 X
1$
#90
0$
#95
b101000 1
b101000 W
b101000 4
b101000 0
b100100 !
b100100 '
b100100 9
b100100 U
b100100 X
1$
#100
0$
#105
b101100 1
b101100 W
b101100 4
b101100 0
b101000 !
b101000 '
b101000 9
b101000 U
b101000 X
1$
#110
0$
#115
b110000 1
b110000 W
b110000 4
b110000 0
b101100 !
b101100 '
b101100 9
b101100 U
b101100 X
1$
#120
0$
#125
b110100 1
b110100 W
b110100 4
b110100 0
b110000 !
b110000 '
b110000 9
b110000 U
b110000 X
1$
#130
0$
#135
b111000 1
b111000 W
b111000 4
b111000 0
b110100 !
b110100 '
b110100 9
b110100 U
b110100 X
1$
#140
0$
#145
b111100 1
b111100 W
b111100 4
b111100 0
b111000 !
b111000 '
b111000 9
b111000 U
b111000 X
1$
#150
0$
#155
b1000000 1
b1000000 W
b1000000 4
b1000000 0
b111100 !
b111100 '
b111100 9
b111100 U
b111100 X
1$
#160
0$
#165
b1000100 1
b1000100 W
b1000100 4
b1000100 0
b1000000 !
b1000000 '
b1000000 9
b1000000 U
b1000000 X
1$
#170
0$
#175
b1001000 1
b1001000 W
b1001000 4
b1001000 0
b1000100 !
b1000100 '
b1000100 9
b1000100 U
b1000100 X
1$
#180
0$
#185
b1001100 1
b1001100 W
b1001100 4
b1001100 0
b1001000 !
b1001000 '
b1001000 9
b1001000 U
b1001000 X
1$
#190
0$
#195
b1010000 1
b1010000 W
b1010000 4
b1010000 0
b1001100 !
b1001100 '
b1001100 9
b1001100 U
b1001100 X
1$
#200
0$
#205
b1010100 1
b1010100 W
b1010100 4
b1010100 0
b1010000 !
b1010000 '
b1010000 9
b1010000 U
b1010000 X
1$
#210
0$
#215
b1011000 1
b1011000 W
b1011000 4
b1011000 0
b1010100 !
b1010100 '
b1010100 9
b1010100 U
b1010100 X
1$
#220
0$
#225
b1011100 1
b1011100 W
b1011100 4
b1011100 0
b1011000 !
b1011000 '
b1011000 9
b1011000 U
b1011000 X
1$
#230
0$
#235
b1100000 1
b1100000 W
b1100000 4
b1100000 0
b1011100 !
b1011100 '
b1011100 9
b1011100 U
b1011100 X
1$
#240
0$
#245
b1100100 1
b1100100 W
b1100100 4
b1100100 0
b1100000 !
b1100000 '
b1100000 9
b1100000 U
b1100000 X
1$
#250
0$
#255
b1101000 1
b1101000 W
b1101000 4
b1101000 0
b1100100 !
b1100100 '
b1100100 9
b1100100 U
b1100100 X
1$
#260
0$
#265
b1101100 1
b1101100 W
b1101100 4
b1101100 0
b1101000 !
b1101000 '
b1101000 9
b1101000 U
b1101000 X
1$
#270
0$
#275
b1110000 1
b1110000 W
b1110000 4
b1110000 0
b1101100 !
b1101100 '
b1101100 9
b1101100 U
b1101100 X
1$
#280
0$
#285
b1110100 1
b1110100 W
b1110100 4
b1110100 0
b1110000 !
b1110000 '
b1110000 9
b1110000 U
b1110000 X
1$
#290
0$
#295
b1111000 1
b1111000 W
b1111000 4
b1111000 0
b1110100 !
b1110100 '
b1110100 9
b1110100 U
b1110100 X
1$
#300
0$
#305
b1111100 1
b1111100 W
b1111100 4
b1111100 0
b1111000 !
b1111000 '
b1111000 9
b1111000 U
b1111000 X
1$
#310
0$
#315
b10000000 1
b10000000 W
b10000000 4
b10000000 0
b1111100 !
b1111100 '
b1111100 9
b1111100 U
b1111100 X
1$
#320
0$
#325
b10000100 1
b10000100 W
b10000100 4
b10000100 0
b10000000 !
b10000000 '
b10000000 9
b10000000 U
b10000000 X
1$
#330
0$
#335
b10001000 1
b10001000 W
b10001000 4
b10001000 0
b10000100 !
b10000100 '
b10000100 9
b10000100 U
b10000100 X
1$
#340
0$
#345
b10001100 1
b10001100 W
b10001100 4
b10001100 0
b10001000 !
b10001000 '
b10001000 9
b10001000 U
b10001000 X
1$
#350
0$
#355
b10010000 1
b10010000 W
b10010000 4
b10010000 0
b10001100 !
b10001100 '
b10001100 9
b10001100 U
b10001100 X
1$
#360
0$
#365
b10010100 1
b10010100 W
b10010100 4
b10010100 0
b10010000 !
b10010000 '
b10010000 9
b10010000 U
b10010000 X
1$
#370
0$
#375
b10011000 1
b10011000 W
b10011000 4
b10011000 0
b10010100 !
b10010100 '
b10010100 9
b10010100 U
b10010100 X
1$
#380
0$
#385
b10011100 1
b10011100 W
b10011100 4
b10011100 0
b10011000 !
b10011000 '
b10011000 9
b10011000 U
b10011000 X
1$
#390
0$
#395
b10100000 1
b10100000 W
b10100000 4
b10100000 0
b10011100 !
b10011100 '
b10011100 9
b10011100 U
b10011100 X
1$
#400
0$
#405
b10100100 1
b10100100 W
b10100100 4
b10100100 0
b10100000 !
b10100000 '
b10100000 9
b10100000 U
b10100000 X
1$
#410
0$
#415
b10101000 1
b10101000 W
b10101000 4
b10101000 0
b10100100 !
b10100100 '
b10100100 9
b10100100 U
b10100100 X
1$
#420
0$
#425
b10101100 1
b10101100 W
b10101100 4
b10101100 0
b10101000 !
b10101000 '
b10101000 9
b10101000 U
b10101000 X
1$
#430
0$
#435
b10110000 1
b10110000 W
b10110000 4
b10110000 0
b10101100 !
b10101100 '
b10101100 9
b10101100 U
b10101100 X
1$
#440
0$
#445
b10110100 1
b10110100 W
b10110100 4
b10110100 0
b10110000 !
b10110000 '
b10110000 9
b10110000 U
b10110000 X
1$
#450
0$
#455
b10111000 1
b10111000 W
b10111000 4
b10111000 0
b10110100 !
b10110100 '
b10110100 9
b10110100 U
b10110100 X
1$
#460
0$
#465
b10111100 1
b10111100 W
b10111100 4
b10111100 0
b10111000 !
b10111000 '
b10111000 9
b10111000 U
b10111000 X
1$
#470
0$
#475
b11000000 1
b11000000 W
b11000000 4
b11000000 0
b10111100 !
b10111100 '
b10111100 9
b10111100 U
b10111100 X
1$
#480
0$
#485
b11000100 1
b11000100 W
b11000100 4
b11000100 0
b11000000 !
b11000000 '
b11000000 9
b11000000 U
b11000000 X
1$
#490
0$
#495
b11001000 1
b11001000 W
b11001000 4
b11001000 0
b11000100 !
b11000100 '
b11000100 9
b11000100 U
b11000100 X
1$
#500
0$
#505
b11001100 1
b11001100 W
b11001100 4
b11001100 0
b11001000 !
b11001000 '
b11001000 9
b11001000 U
b11001000 X
1$
#510
0$
#515
b11010000 1
b11010000 W
b11010000 4
b11010000 0
b11001100 !
b11001100 '
b11001100 9
b11001100 U
b11001100 X
1$
#520
0$
#525
b11010100 1
b11010100 W
b11010100 4
b11010100 0
b11010000 !
b11010000 '
b11010000 9
b11010000 U
b11010000 X
1$
#530
0$
#535
b11011000 1
b11011000 W
b11011000 4
b11011000 0
b11010100 !
b11010100 '
b11010100 9
b11010100 U
b11010100 X
1$
#540
0$
