include/defines.vh
/*
-------------------------------------------------------------------------
Disciplina: Arquitetura e Organização de Computadores - 2025.2
Atividade: Projeto 02 - Implementação de MIPS em Verilog
Grupo: [INSERIR NOMES AQUI]
Arquivo: defines.vh
Descrição: Definições de macros (constantes) para Opcodes, Functs e ALU.
-------------------------------------------------------------------------
*/
`ifndef DEFINES_VH
`define DEFINES_VH

// --- PARÂMETROS DE MEMÓRIA ---
`define IMEM_SIZE 1024
`define DMEM_SIZE 1024

// --- ALUOp CODES (Control -> ALU Ctrl) ---
`define ALUOP_RTYPE         2'b10
`define ALUOP_BEQ_BNE       2'b01
`define ALUOP_LW_SW_ADDI    2'b00
`define ALUOP_ANDI_ORI_XORI 2'b11

// --- ULA INTERNAL CODES (ALU Ctrl -> ULA) ---
`define ALU_ADD   4'b0001
`define ALU_SUB   4'b0010
`define ALU_AND   4'b0011
`define ALU_OR    4'b0100
`define ALU_XOR   4'b0101
`define ALU_NOR   4'b0110
`define ALU_SLT   4'b0111
`define ALU_SLTU  4'b1000
`define ALU_SLL   4'b1001
`define ALU_SRL   4'b1010
`define ALU_SRA   4'b1011
`define ALU_SLLV  4'b1100
`define ALU_SRLV  4'b1101
`define ALU_SRAV  4'b1110
`define ALU_JR    4'b1111

// --- FUNCT FOR R-TYPE (6 bits) ---
`define FUNCT_ADD   6'b100000
`define FUNCT_SUB   6'b100010
`define FUNCT_AND   6'b100100
`define FUNCT_OR    6'b100101
`define FUNCT_XOR   6'b100110
`define FUNCT_NOR   6'b100111
`define FUNCT_SLT   6'b101010
`define FUNCT_SLTU  6'b101011
`define FUNCT_SLL   6'b000000
`define FUNCT_SRL   6'b000010
`define FUNCT_SRA   6'b000011
`define FUNCT_SLLV  6'b000100
`define FUNCT_SRLV  6'b000110
`define FUNCT_SRAV  6'b000111
`define FUNCT_JR    6'b001000

// --- MIPS OPCODES (6 bits) ---
`define MIPS_RTYPE  6'b000000
`define MIPS_ADDI   6'b001000
`define MIPS_ANDI   6'b001100
`define MIPS_ORI    6'b001101
`define MIPS_XORI   6'b001110
`define MIPS_BEQ    6'b000100
`define MIPS_BNE    6'b000101
`define MIPS_SLTI   6'b001010
`define MIPS_SLTIU  6'b001011
`define MIPS_LUI    6'b001111
`define MIPS_LW     6'b100011
`define MIPS_SW     6'b101011
`define MIPS_J      6'b000010
`define MIPS_JAL    6'b000011

`endif

src/control.v
/*
-------------------------------------------------------------------------
Disciplina: Arquitetura e Organização de Computadores - 2025.2
Atividade: Projeto 02 - Implementação de MIPS em Verilog
Grupo: Aldo Ferreira, Andressa Américo, Carlos de Souza, Gustavo do Monte
Arquivo: control.v
Descrição: Decodifica o Opcode e gera sinais de controle para o Datapath.
-------------------------------------------------------------------------
*/
`include "defines.vh"

module control(
  input [5:0] opcode,
  input [5:0] funct,
  output reg RegDst, Jump, Branch, MemRead, MemtoReg,
  output reg [1:0] ALUOp,
  output reg MemWrite, ALUSrc, RegWrite, Jr, ExtOp, JalEn, LuiEn
);

  // Bloco combinacional: sensível a qualquer mudança nas entradas
  always @(*) begin
    
    // ---------------------------------------------------------
    // 1. Reset Padrão 
    // Inicializa todos os sinais em 0 ou valores seguros antes de decodificar.
    // Garante que sinais não usados em uma instrução fiquem desligados.
    // ---------------------------------------------------------
    RegDst=0; Jump=0; Branch=0; MemRead=0; MemtoReg=0;
    ALUOp=`ALUOP_LW_SW_ADDI; MemWrite=0; ALUSrc=0; RegWrite=0;
    Jr=0; ExtOp=1; JalEn=0; LuiEn=0; // ExtOp=1 por padrão (Extensão de Sinal)

    // ---------------------------------------------------------
    // 2. Decodificação do Opcode
    // ---------------------------------------------------------
    case (opcode)
      
      // --- Instruções Tipo-R ---
      `MIPS_RTYPE: begin
        RegDst = 1;      // Destino é o registrador Rd (bits 15-11)
        RegWrite = 1;    // Habilita escrita no banco de registradores
        ALUOp = `ALUOP_RTYPE; // Avisa a ULA_Ctrl para olhar o campo 'funct'
        
        // Caso especial: JR (Jump Register) é Tipo-R mas afeta o fluxo
        if (funct == `FUNCT_JR) begin
            Jr = 1;
            RegWrite = 0; // JR não escreve em registrador
        end
      end

      // --- Instruções Tipo-I (Aritmética e Lógica) ---
      `MIPS_ADDI: begin 
          ALUSrc = 1;    // 2º operando da ULA é o Imediato
          RegWrite = 1;  // Escreve o resultado
      end
      
      // Lógicas: Usam Extensão de Zero (ExtOp = 0) pois não têm sinal
      `MIPS_ANDI: begin ALUSrc = 1; RegWrite = 1; ExtOp = 0; ALUOp = `ALUOP_ANDI_ORI_XORI; end
      `MIPS_ORI:  begin ALUSrc = 1; RegWrite = 1; ExtOp = 0; ALUOp = `ALUOP_ANDI_ORI_XORI; end
      `MIPS_XORI: begin ALUSrc = 1; RegWrite = 1; ExtOp = 0; ALUOp = `ALUOP_ANDI_ORI_XORI; end

      // --- Instruções de Branch (Desvio Condicional) ---
      `MIPS_BEQ:  begin Branch = 1; ALUOp = `ALUOP_BEQ_BNE; end // ULA faz subtração
      `MIPS_BNE:  begin Branch = 1; ALUOp = `ALUOP_BEQ_BNE; end // ULA faz subtração

      // --- Instruções de Comparação Imediata ---
      `MIPS_SLTI: begin ALUSrc = 1; RegDst = 0; RegWrite = 1; ALUOp = 2'b10; end
      `MIPS_SLTIU:begin ALUSrc = 1; RegDst = 0; RegWrite = 1; ALUOp = 2'b11; end

      // --- Instrução LUI (Load Upper Immediate) ---
      `MIPS_LUI:  begin 
          ALUSrc = 1; 
          RegWrite = 1; 
          LuiEn = 1; // Habilita o deslocamento de 16 bits no datapath
      end

      // --- Acesso à Memória ---
      `MIPS_LW:   begin 
          ALUSrc = 1; 
          MemtoReg = 1; // O dado vem da Memória, não da ULA
          RegWrite = 1; 
          MemRead = 1;  // Habilita leitura da RAM
      end
      
      `MIPS_SW:   begin 
          ALUSrc = 1; 
          MemWrite = 1; // Habilita escrita na RAM
      end

      // --- Instruções de Salto (Tipo-J) ---
      `MIPS_J:    begin Jump = 1; end
      
      `MIPS_JAL:  begin 
          Jump = 1; 
          RegWrite = 1; // Precisa escrever o endereço de retorno ($ra)
          JalEn = 1;    // Habilita a lógica de salvar PC+4 em $31
      end

      default: begin end
    endcase
  end
endmodule

src/d_mem.v
/*
-------------------------------------------------------------------------
Disciplina: Arquitetura e Organização de Computadores - 2025.2
Atividade: Projeto 02 - Implementação de MIPS em Verilog
Grupo: Aldo Ferreira, Andressa Américo, Carlos de Souza, Gustavo do Monte
Arquivo: d_mem.v
Descrição: Memória RAM para armazenamento de dados (Load/Store).
-------------------------------------------------------------------------
*/
`include "defines.vh"

module d_mem(
  input clock,
  input MemRead,          // Habilita leitura
  input MemWrite,         // Habilita escrita
  input [31:0] address,   // Endereço
  input [31:0] WriteData, // Dado a ser escrito
  output [31:0] ReadData  // Dado lido
);
  reg [31:0] mem [0:`DMEM_SIZE-1];
  integer k;

  initial begin
     for (k=0; k<`DMEM_SIZE; k=k+1) mem[k] = 32'b0;
  end

  assign ReadData = MemRead ? mem[address[11:2]] : 32'bz;
  
  always @(posedge clock) begin
    if (MemWrite) 
      mem[address[11:2]] <= WriteData;
  end
endmodule

src/ula.v
/*
-------------------------------------------------------------------------
Disciplina: Arquitetura e Organização de Computadores - 2025.2
Atividade: Projeto 02 - Implementação de MIPS em Verilog
Grupo: Aldo Ferreira, Andressa Américo, Carlos de Souza, Gustavo do Monte
Arquivo: ula.v
Descrição: Executa operações aritméticas e lógicas baseadas no sinal OP.
-------------------------------------------------------------------------
*/
`include "defines.vh"

module ula( 
  input [31:0] In1, In2,   // Operandos
  input [4:0]  shamt,      // Shift amount
  input [3:0]  OP,         // Código da operação
  output reg [31:0] result,// Resultado
  output wire Zero_Flag    // Flag Zero
);
  always @(*) begin
    case (OP)
      `ALU_ADD:   result = In1 + In2;
      `ALU_SUB:   result = In1 - In2;
      `ALU_AND:   result = In1 & In2;
      `ALU_OR:    result = In1 | In2;
      `ALU_XOR:   result = In1 ^ In2;
      `ALU_NOR:   result = ~(In1 | In2);
      `ALU_SLT:   result = ($signed(In1) < $signed(In2)) ? 1 : 0;
      `ALU_SLTU:  result = (In1 < In2) ? 1 : 0;
      `ALU_SLL:   result = In2 << shamt;
      `ALU_SRL:   result = In2 >> shamt;
      `ALU_SRA:   result = $signed(In2) >>> shamt;
      `ALU_SLLV:  result = In2 << In1[4:0];
      `ALU_SRLV:  result = In2 >> In1[4:0];
      `ALU_SRAV:  result = $signed(In2) >>> In1[4:0];
      `ALU_JR:    result = In1; 
      default:    result = 0;
    endcase
  end
  
  assign Zero_Flag = (result == 0);
endmodule

src/ula_ctrl.v
/*
-------------------------------------------------------------------------
Disciplina: Arquitetura e Organização de Computadores - 2025.2
Atividade: Projeto 02 - Implementação de MIPS em Verilog
Grupo: Aldo Ferreira, Andressa Américo, Carlos de Souza, Gustavo do Monte
Arquivo: ula_ctrl.v
Descrição: Decodifica ALUOp e Funct para gerar o sinal de controle da ULA.
-------------------------------------------------------------------------
*/
`include "defines.vh"

module ula_ctrl(
  input [1:0] ALUOp,     // Vindo da Unidade de Controle
  input [5:0] funct,     // Campo funct da instrução
  output reg [3:0] OP_ula // Código para a ULA
);
  always @(*) begin
    case (ALUOp)
      `ALUOP_LW_SW_ADDI: OP_ula = `ALU_ADD; 
      `ALUOP_BEQ_BNE:    OP_ula = `ALU_SUB; 
      `ALUOP_ANDI_ORI_XORI: OP_ula = `ALU_OR; // Assumindo OR para imediatos lógicos genéricos
      
      `ALUOP_RTYPE: begin
        case (funct)
          `FUNCT_ADD:  OP_ula = `ALU_ADD;
          `FUNCT_SUB:  OP_ula = `ALU_SUB;
          `FUNCT_AND:  OP_ula = `ALU_AND;
          `FUNCT_OR:   OP_ula = `ALU_OR;
          `FUNCT_XOR:  OP_ula = `ALU_XOR;
          `FUNCT_NOR:  OP_ula = `ALU_NOR;
          `FUNCT_SLT:  OP_ula = `ALU_SLT;
          `FUNCT_SLTU: OP_ula = `ALU_SLTU;
          `FUNCT_SLL:  OP_ula = `ALU_SLL;
          `FUNCT_SRL:  OP_ula = `ALU_SRL;
          `FUNCT_SRA:  OP_ula = `ALU_SRA;
          `FUNCT_SLLV: OP_ula = `ALU_SLLV;
          `FUNCT_SRLV: OP_ula = `ALU_SRLV;
          `FUNCT_SRAV: OP_ula = `ALU_SRAV;
          `FUNCT_JR:   OP_ula = `ALU_JR;
          default:     OP_ula = `ALU_ADD;
        endcase
      end
      default: OP_ula = `ALU_ADD;
    endcase
  end
endmodule

src/sign_extend.v
/*
-------------------------------------------------------------------------
Disciplina: Arquitetura e Organização de Computadores - 2025.2
Atividade: Projeto 02 - Implementação de MIPS em Verilog
Grupo: Aldo Ferreira, Andressa Américo, Carlos de Souza, Gustavo do Monte
Arquivo: sign_extend.v
Descrição: Estende imediatos de 16 bits para 32 bits (com sinal ou zero).
-------------------------------------------------------------------------
*/
module sign_extend(
  input [15:0] imm,
  input ExtOp,       // 1 = Sinal, 0 = Zero
  output reg [31:0] ext_out
);
  always @(*) begin
    if (ExtOp) 
      ext_out = {{16{imm[15]}}, imm}; // Extensão de sinal
    else       
      ext_out = {16'b0, imm};         // Extensão de zero
  end
endmodule

src/regfile.v
/*
-------------------------------------------------------------------------
Disciplina: Arquitetura e Organização de Computadores - 2025.2
Atividade: Projeto 02 - Implementação de MIPS em Verilog
Grupo: Aldo Ferreira, Andressa Américo, Carlos de Souza, Gustavo do Monte
Arquivo: regfile.v
Descrição: Banco com 32 registradores de 32 bits. Reg $0 é sempre zero.
-------------------------------------------------------------------------
*/
module regfile(
  input clock,
  input reset,
  input RegWrite,            // Habilita escrita
  input [4:0] ReadAddr1,     // Endereço rs
  input [4:0] ReadAddr2,     // Endereço rt
  input [4:0] WriteAddr,     // Endereço rd (ou rt em tipo-I)
  input [31:0] WriteData,    // Dado a ser escrito
  output [31:0] ReadData1,   // Saída rs
  output [31:0] ReadData2    // Saída rt
);
  reg [31:0] registers [0:31]; 
  integer i;

  // Leitura Assíncrona
  assign ReadData1 = (ReadAddr1 == 0) ? 32'b0 : registers[ReadAddr1];
  assign ReadData2 = (ReadAddr2 == 0) ? 32'b0 : registers[ReadAddr2];

  // Escrita Síncrona
  always @(posedge clock or posedge reset) begin
    if (reset) begin
      for (i=0; i<32; i=i+1) registers[i] <= 0;
    end 
    else if (RegWrite && WriteAddr != 0) begin
      registers[WriteAddr] <= WriteData;
    end
  end
endmodule

src/i_mem.v
/*
-------------------------------------------------------------------------
Disciplina: Arquitetura e Organização de Computadores - 2025.2
Atividade: Projeto 02 - Implementação de MIPS em Verilog
Grupo: Aldo Ferreira, Andressa Américo, Carlos de Souza, Gustavo do Monte
Arquivo: i_mem.v
Descrição: Memória de Instrução (ROM). Lê o programa de 'instruction.list'.
-------------------------------------------------------------------------
*/
`include "defines.vh"

module i_mem(
  input  wire [31:0] address,   // Endereço vindo do PC
  output wire [31:0] i_out      // Instrução lida
);
  reg [31:0] mem [0:`IMEM_SIZE-1];
  integer i;

  initial begin
    // Inicializa com zeros
    for (i = 0; i < `IMEM_SIZE; i = i + 1) mem[i] = 32'b0;

    // Carrega o arquivo externo (Requisito do PDF)
    $readmemb("instruction.list", mem);
  end
  
  // Leitura assíncrona (word align: address / 4)
  assign i_out = mem[address[11:2]]; 
endmodule

src/pc.v
/*
-------------------------------------------------------------------------
Disciplina: Arquitetura e Organização de Computadores - 2025.2
Atividade: Projeto 02 - Implementação de MIPS em Verilog
Grupo: Aldo Ferreira, Andressa Américo, Carlos de Souza, Gustavo do Monte
Arquivo: pc.v
Descrição: Registrador de 32 bits que armazena o endereço da instrução atual.
-------------------------------------------------------------------------
*/
module pc(
  input clock,          // Clock do sistema
  input reset,          // Reset global
  input [31:0] nextPC,  // Próximo endereço calculado
  output reg [31:0] PC  // Endereço atual
);
  always @(posedge clock or posedge reset) begin
    if (reset) 
      PC <= 32'h00000000; 
    else       
      PC <= nextPC;       
  end
endmodule

src/mips.v
/*
-------------------------------------------------------------------------
Disciplina: Arquitetura e Organização de Computadores - 2025.2
Atividade: Projeto 02 - Implementação de MIPS em Verilog
Grupo: Aldo Ferreira, Andressa Américo, Carlos de Souza, Gustavo do Monte
Arquivo: mips.v
Descrição: Módulo Top-Level. Integra Datapath e Controle.
-------------------------------------------------------------------------
*/
`include "defines.vh"

module mips(
  input clock,
  input reset,
  output [31:0] PCOut,
  output [31:0] ALUResultOut,
  output [31:0] MemOut
);
  // Fios de interconexão
  wire [31:0] PC, nextPC, instruction;
  wire [31:0] read_data1, read_data2, write_data;
  wire [31:0] sign_ext_out, alu_in2, dmem_out;
  wire RegDst, Jump, Branch, MemRead, MemtoReg, MemWrite, ALUSrc, RegWrite, Jr, ExtOp, JalEn, LuiEn;
  wire [1:0] ALUOp;
  wire [3:0] alu_control;
  wire zero_flag;

  // 1. Contador de Programa (PC)
  pc pc_inst(.clock(clock), .reset(reset), .nextPC(nextPC), .PC(PC));
  assign PCOut = PC;
  
  // 2. Memória de Instrução
  i_mem imem(.address(PC), .i_out(instruction));
  
  // Mux do registrador de escrita
  wire [4:0] write_reg = JalEn ? 5'b11111 : (RegDst ? instruction[15:11] : instruction[20:16]);
  
  // 3. Banco de Registradores
  regfile regs(
    .clock(clock), .reset(reset), .RegWrite(RegWrite),
    .ReadAddr1(instruction[25:21]), .ReadAddr2(instruction[20:16]),
    .WriteAddr(write_reg), .WriteData(write_data),
    .ReadData1(read_data1), .ReadData2(read_data2)
  );
  
  // 4. Extensão de Sinal
  sign_extend ext(.imm(instruction[15:0]), .ExtOp(ExtOp), .ext_out(sign_ext_out));
  
  // Mux da entrada B da ULA
  assign alu_in2 = ALUSrc ? sign_ext_out : read_data2;
  
  // 5. Controle e ULA
  ula_ctrl uctrl(.ALUOp(ALUOp), .funct(instruction[5:0]), .OP_ula(alu_control));
  
  ula alu(
    .In1(read_data1), .In2(alu_in2), .shamt(instruction[10:6]),
    .OP(alu_control), .result(ALUResultOut), .Zero_Flag(zero_flag)
  );
  
  // 6. Memória de Dados
  d_mem dmem(
    .clock(clock), .MemRead(MemRead), .MemWrite(MemWrite),
    .address(ALUResultOut), .WriteData(read_data2), .ReadData(dmem_out)
  );
  assign MemOut = dmem_out;
  
  // 7. Lógica de Próximo PC
  wire [31:0] pc_plus4 = PC + 4;
  wire [31:0] branch_target = pc_plus4 + {sign_ext_out[29:0], 2'b00};
  wire is_jr = (instruction[31:26] == `MIPS_RTYPE) && (instruction[5:0] == `FUNCT_JR);
  wire branch_taken = Branch & (
    (instruction[31:26] == `MIPS_BEQ & zero_flag) | 
    (instruction[31:26] == `MIPS_BNE & ~zero_flag)
  );
  
  assign nextPC = is_jr ? read_data1 :
                  Jump  ? {pc_plus4[31:28], instruction[25:0], 2'b00} :
                  branch_taken ? branch_target :
                  pc_plus4;
  
  assign write_data = JalEn ? pc_plus4 : 
                      LuiEn ? {instruction[15:0], 16'b0} : 
                      MemtoReg ? dmem_out : ALUResultOut;
  
  // 8. Unidade de Controle Principal
  control ctrl(
    .opcode(instruction[31:26]), .funct(instruction[5:0]),
    .RegDst(RegDst), .Jump(Jump), .Branch(Branch),
    .MemRead(MemRead), .MemtoReg(MemtoReg), .ALUOp(ALUOp),
    .MemWrite(MemWrite), .ALUSrc(ALUSrc), .RegWrite(RegWrite),
    .Jr(Jr), .ExtOp(ExtOp), .JalEn(JalEn), .LuiEn(LuiEn)
  );

endmodule

test/testbench.v
/*
-------------------------------------------------------------------------
Disciplina: Arquitetura e Organização de Computadores - 2025.2
Atividade: Projeto 02 - Implementação de MIPS em Verilog
Grupo: Aldo Ferreira, Andressa Américo, Carlos de Souza, Gustavo do Monte
Arquivo: testbench.v
Descrição: Gera clock/reset e monitora a execução do processador.
           Versão ajustada para exibir 0 em vez de Z na leitura de memória.
-------------------------------------------------------------------------
*/
`include "defines.vh"

module testbench;
  reg clock;
  reg reset;
  wire [31:0] PCOut;
  wire [31:0] ALUResultOut;
  wire [31:0] MemOut;

  // Instância do DUT (Device Under Test) - O Processador MIPS
  mips dut(
    .clock(clock),
    .reset(reset),
    .PCOut(PCOut),
    .ALUResultOut(ALUResultOut),
    .MemOut(MemOut)
  );

  // Geração de Clock (Período = 10ns)
  initial begin
    clock = 0;
    forever #5 clock = ~clock;
  end

  // Sequência de Controle da Simulação
  initial begin
    // Configura arquivo para visualização de ondas no GTKWave
    $dumpfile("mips_waveform.vcd");
    $dumpvars(0, testbench);

    // Reset inicial
    $display(">>> Iniciando Simulação...");
    reset = 1;
    #10;
    reset = 0;
    
    // Tempo de simulação calibrado para a lista de 64 instruções
    #800; 
    
    $display("---------------------------------------------------------");
    $display("Simulação finalizada por limite de tempo.");
    $finish;
  end

  // Monitoramento (Imprime no terminal a cada ciclo de clock)
  always @(posedge clock) begin
    if (!reset) begin
      // AQUI ESTÁ A MUDANÇA:
      // Usamos (dut.MemRead ? MemOut : 32'h0)
      // Se estiver lendo (MemRead=1), mostra o valor real. Se não, mostra 0.
      $write("Time: %4d | PC: %h | Instr: %h | ULA: %h | Mem: %h", 
             $time, PCOut, dut.instruction, ALUResultOut, 
             (dut.MemRead ? MemOut : 32'h0));

      // Feedback específico para operações de Memória (Logs extras)
      if (dut.MemWrite) begin
          $display(" | [MEM WRITE] Escreveu %h no end. %h", dut.dmem.WriteData, ALUResultOut);
      end
      else if (dut.MemRead) begin
          $display(" | [MEM READ] Leu %h do end. %h", MemOut, ALUResultOut);
      end
      else begin
          $display(""); // Apenas pular linha para manter a formatação
      end
    end
  end
endmodule

mips_waveform.vcd
$date
	Tue Dec 09 15:01:26 2025
$end
$version
	Icarus Verilog
$end
$timescale
	1s
$end
$scope module testbench $end
$var wire 32 ! PCOut [31:0] $end
$var wire 32 " MemOut [31:0] $end
$var wire 32 # ALUResultOut [31:0] $end
$var reg 1 $ clock $end
$var reg 1 % reset $end
$scope module dut $end
$var wire 32 & MemOut [31:0] $end
$var wire 32 ' PCOut [31:0] $end
$var wire 1 ( branch_taken $end
$var wire 1 $ clock $end
$var wire 1 ) is_jr $end
$var wire 1 % reset $end
$var wire 1 * zero_flag $end
$var wire 5 + write_reg [4:0] $end
$var wire 32 , write_data [31:0] $end
$var wire 32 - sign_ext_out [31:0] $end
$var wire 32 . read_data2 [31:0] $end
$var wire 32 / read_data1 [31:0] $end
$var wire 32 0 pc_plus4 [31:0] $end
$var wire 32 1 nextPC [31:0] $end
$var wire 32 2 instruction [31:0] $end
$var wire 32 3 dmem_out [31:0] $end
$var wire 32 4 branch_target [31:0] $end
$var wire 32 5 alu_in2 [31:0] $end
$var wire 4 6 alu_control [3:0] $end
$var wire 1 7 RegWrite $end
$var wire 1 8 RegDst $end
$var wire 32 9 PC [31:0] $end
$var wire 1 : MemtoReg $end
$var wire 1 ; MemWrite $end
$var wire 1 < MemRead $end
$var wire 1 = LuiEn $end
$var wire 1 > Jump $end
$var wire 1 ? Jr $end
$var wire 1 @ JalEn $end
$var wire 1 A ExtOp $end
$var wire 1 B Branch $end
$var wire 1 C ALUSrc $end
$var wire 32 D ALUResultOut [31:0] $end
$var wire 2 E ALUOp [1:0] $end
$scope module alu $end
$var wire 32 F In2 [31:0] $end
$var wire 5 G shamt [4:0] $end
$var wire 1 * Zero_Flag $end
$var wire 4 H OP [3:0] $end
$var wire 32 I In1 [31:0] $end
$var reg 32 J result [31:0] $end
$upscope $end
$scope module ctrl $end
$var wire 6 K funct [5:0] $end
$var wire 6 L opcode [5:0] $end
$var reg 2 M ALUOp [1:0] $end
$var reg 1 C ALUSrc $end
$var reg 1 B Branch $end
$var reg 1 A ExtOp $end
$var reg 1 @ JalEn $end
$var reg 1 ? Jr $end
$var reg 1 > Jump $end
$var reg 1 = LuiEn $end
$var reg 1 < MemRead $end
$var reg 1 ; MemWrite $end
$var reg 1 : MemtoReg $end
$var reg 1 8 RegDst $end
$var reg 1 7 RegWrite $end
$upscope $end
$scope module dmem $end
$var wire 1 < MemRead $end
$var wire 1 ; MemWrite $end
$var wire 32 N address [31:0] $end
$var wire 1 $ clock $end
$var wire 32 O WriteData [31:0] $end
$var wire 32 P ReadData [31:0] $end
$var integer 32 Q k [31:0] $end
$upscope $end
$scope module ext $end
$var wire 1 A ExtOp $end
$var wire 16 R imm [15:0] $end
$var reg 32 S ext_out [31:0] $end
$upscope $end
$scope module imem $end
$var wire 32 T i_out [31:0] $end
$var wire 32 U address [31:0] $end
$var integer 32 V i [31:0] $end
$upscope $end
$scope module pc_inst $end
$var wire 1 $ clock $end
$var wire 32 W nextPC [31:0] $end
$var wire 1 % reset $end
$var reg 32 X PC [31:0] $end
$upscope $end
$scope module regs $end
$var wire 5 Y ReadAddr1 [4:0] $end
$var wire 5 Z ReadAddr2 [4:0] $end
$var wire 1 7 RegWrite $end
$var wire 5 [ WriteAddr [4:0] $end
$var wire 32 \ WriteData [31:0] $end
$var wire 1 $ clock $end
$var wire 1 % reset $end
$var wire 32 ] ReadData2 [31:0] $end
$var wire 32 ^ ReadData1 [31:0] $end
$var integer 32 _ i [31:0] $end
$upscope $end
$scope module uctrl $end
$var wire 2 ` ALUOp [1:0] $end
$var wire 6 a funct [5:0] $end
$var reg 4 b OP_ula [3:0] $end
$upscope $end
$upscope $end
$upscope $end
$enddefinitions $end
$comment Show the parameter values. $end
$dumpall
$end
#0
$dumpvars
b1 b
b1111 a
b0 `
b100000 _
b0 ^
b0 ]
b11110000000000000000 \
b1 [
b1 Z
b0 Y
b0 X
b100 W
b10000000000 V
b0 U
b111100000000010000000000001111 T
b1111 S
b1111 R
b10000000000 Q
bz P
b0 O
b1111 N
b0 M
b1111 L
b1111 K
b1111 J
b0 I
b1 H
b0 G
b1111 F
b0 E
b1111 D
1C
0B
1A
0@
0?
0>
1=
0<
0;
0:
b0 9
08
17
b1 6
b1111 5
b1000000 4
bz 3
b111100000000010000000000001111 2
b100 1
b100 0
b0 /
b0 .
b1111 -
b11110000000000000000 ,
b1 +
0*
0)
0(
b0 '
bz &
1%
0$
b1111 #
bz "
b0 !
$end
#5
b100000 _
1$
#10
0$
0%
#15
b100 6
b100 H
b100 b
b11111010000000000000 ,
b11111010000000000000 \
b1010000000000000 5
b1010000000000000 F
b11111010000000000000 #
b11111010000000000000 D
b11111010000000000000 J
b11111010000000000000 N
b11 E
b11 M
b11 `
0A
0=
17
1C
b1010000000000000 -
b1010000000000000 S
b11110000000000000000 /
b11110000000000000000 I
b11110000000000000000 ^
b1000 1
b1000 W
b0 K
b1101 L
b0 a
b1010000000000000 R
b1 Y
b110100001000011010000000000000 2
b110100001000011010000000000000 T
b11110000000000000000 .
b11110000000000000000 O
b11110000000000000000 ]
b101000000000001000 4
b1000 0
b100 !
b100 '
b100 9
b100 U
b100 X
1$
#20
0$
#25
b11111010000000000000 ,
b11111010000000000000 \
b11001 +
b11001 [
b1 6
b1 H
b1 b
b11111010000000000000 5
b11111010000000000000 F
b11111010000000000000 #
b11111010000000000000 D
b11111010000000000000 J
b11111010000000000000 N
18
1A
17
0C
b10 E
b10 M
b10 `
b11111111111111111100100000100000 -
b11111111111111111100100000100000 S
b1100 1
b1100 W
b100000 K
b0 L
b100000 a
b1100100000100000 R
b0 Y
b0 /
b0 I
b0 ^
b11111010000000000000 .
b11111010000000000000 O
b11111010000000000000 ]
b11100100000100000 2
b11100100000100000 T
b11111111111111110010000010001100 4
b1100 0
b1000 !
b1000 '
b1000 9
b1000 U
b1000 X
1$
#30
0$
#35
b11111010000000000001 ,
b11111010000000000001 \
b1 5
b1 F
b11111010000000000001 #
b11111010000000000001 D
b11111010000000000001 J
b11111010000000000001 N
b11001 +
b11001 [
1C
17
b0 E
b0 M
b0 `
08
b1 -
b1 S
b11111010000000000000 /
b11111010000000000000 I
b11111010000000000000 ^
b10000 1
b10000 W
b1 K
b1000 L
b1 a
b1 R
b11001 Z
b11001 Y
b100011001110010000000000000001 2
b100011001110010000000000000001 T
b10100 4
b10000 0
b1100 !
b1100 '
b1100 9
b1100 U
b1100 X
1$
#40
0$
#45
b10100 ,
b10100 \
b10100 5
b10100 F
b10000 +
b10000 [
17
1C
b10100 -
b10100 S
b10100 1
b10100 W
b10100 #
b10100 D
b10100 J
b10100 N
b10100 K
b10100 a
b10100 R
b10000 Z
b0 Y
b0 /
b0 I
b0 ^
b0 .
b0 O
b0 ]
b100000000100000000000000010100 2
b100000000100000000000000010100 T
b1100100 4
b10100 0
b10000 !
b10000 '
b10000 9
b10000 U
b10000 X
1$
#50
0$
#55
b1111 ,
b1111 \
b1111 #
b1111 D
b1111 J
b1111 N
b1111 5
b1111 F
b10001 +
b10001 [
17
1C
b1111 -
b1111 S
b11000 1
b11000 W
b1111 K
b1111 a
b1111 R
b10001 Z
b100000000100010000000000001111 2
b100000000100010000000000001111 T
b0 .
b0 O
b0 ]
b1010100 4
b11000 0
b10100 !
b10100 '
b10100 9
b10100 U
b10100 X
1$
#60
0$
#65
b100011 ,
b100011 \
b1000 +
b1000 [
b100011 #
b100011 D
b100011 J
b100011 N
b10 E
b10 M
b10 `
18
17
0C
b100000000100000 -
b100000000100000 S
b10100 /
b10100 I
b10100 ^
b11100 1
b11100 W
b100000 K
b0 L
b100000 a
b100000000100000 R
b10000 Y
b1111 .
b1111 O
b1111 ]
b10000100010100000000100000 2
b10000100010100000000100000 T
b10000000010011100 4
b11100 0
b11000 !
b11000 '
b11000 9
b11000 U
b11000 X
1$
#70
0$
#75
b101 ,
b101 \
b101 #
b101 D
b101 J
b101 N
b1001 +
b1001 [
17
b10 E
b10 M
b10 `
18
b10 6
b10 H
b10 b
b100100000100010 -
b100100000100010 S
b100000 1
b100000 W
b100010 K
b100010 a
b100100000100010 R
b10000100010100100000100010 2
b10000100010100100000100010 T
b10010000010101000 4
b100000 0
b11100 !
b11100 '
b11100 9
b11100 U
b11100 X
1$
#80
0$
#85
b101000 ,
b101000 \
b101000 #
b101000 D
b101000 J
b101000 N
b10100 5
b10100 F
b1010 +
b1010 [
1C
17
b0 E
b0 M
b0 `
08
b1 6
b1 H
b1 b
b10100 -
b10100 S
b0 .
b0 O
b0 ]
b100100 1
b100100 W
b10100 K
b1000 L
b10100 a
b10100 R
b1010 Z
b100010000010100000000000010100 2
b100010000010100000000000010100 T
b1110100 4
b100100 0
b100000 !
b100000 '
b100000 9
b100000 U
b100000 X
1$
#90
0$
#95
b100 ,
b100 \
b100 #
b100 D
b100 J
b100 N
b11 6
b11 H
b11 b
b1111 5
b1111 F
b1011 +
b1011 [
b10 E
b10 M
b10 `
18
17
0C
b101100000100100 -
b101100000100100 S
b101000 1
b101000 W
b100100 K
b0 L
b100100 a
b101100000100100 R
b10001 Z
b10000100010101100000100100 2
b10000100010101100000100100 T
b1111 .
b1111 O
b1111 ]
b10110000010111000 4
b101000 0
b100100 !
b100100 '
b100100 9
b100100 U
b100100 X
1$
#100
0$
#105
b11111 ,
b11111 \
b11111 #
b11111 D
b11111 J
b11111 N
b1100 +
b1100 [
17
b10 E
b10 M
b10 `
18
b100 6
b100 H
b100 b
b110000000100101 -
b110000000100101 S
b101100 1
b101100 W
b100101 K
b100101 a
b110000000100101 R
b10000100010110000000100101 2
b10000100010110000000100101 T
b11000000011000000 4
b101100 0
b101000 !
b101000 '
b101000 9
b101000 U
b101000 X
1$
#110
0$
#115
b11011 ,
b11011 \
b11011 #
b11011 D
b11011 J
b11011 N
b1101 +
b1101 [
17
b10 E
b10 M
b10 `
18
b101 6
b101 H
b101 b
b110100000100110 -
b110100000100110 S
b110000 1
b110000 W
b100110 K
b100110 a
b110100000100110 R
b10000100010110100000100110 2
b10000100010110100000100110 T
b11010000011001000 4
b110000 0
b101100 !
b101100 '
b101100 9
b101100 U
b101100 X
1$
#120
0$
